receipt_dynamo/__init__.py
receipt_dynamo/data/OCRSwift.swift
receipt_dynamo/data/__init__.py
receipt_dynamo/data/_cluster.py
receipt_dynamo/data/_corner_process.py
receipt_dynamo/data/_geometry.py
receipt_dynamo/data/_gpt.py
receipt_dynamo/data/_gpt_initial_tagging.py
receipt_dynamo/data/_gpt_validation.py
receipt_dynamo/data/_image.py
receipt_dynamo/data/_letter.py
receipt_dynamo/data/_line.py
receipt_dynamo/data/_ocr.py
receipt_dynamo/data/_pulumi.py
receipt_dynamo/data/_receipt.py
receipt_dynamo/data/_receipt_letter.py
receipt_dynamo/data/_receipt_line.py
receipt_dynamo/data/_receipt_window.py
receipt_dynamo/data/_receipt_word.py
receipt_dynamo/data/_receipt_word_tag.py
receipt_dynamo/data/_word.py
receipt_dynamo/data/_word_tag.py
receipt_dynamo/data/dynamo_client.py
receipt_dynamo/data/export_image.py
receipt_dynamo/data/import_image.py
receipt_dynamo/data/process.py
receipt_dynamo/data/process_picture.py
receipt_dynamo/data/validate.py
receipt_dynamo/entities/__init__.py
receipt_dynamo/entities/gpt_initial_tagging.py
receipt_dynamo/entities/gpt_validation.py
receipt_dynamo/entities/image.py
receipt_dynamo/entities/letter.py
receipt_dynamo/entities/line.py
receipt_dynamo/entities/receipt.py
receipt_dynamo/entities/receipt_letter.py
receipt_dynamo/entities/receipt_line.py
receipt_dynamo/entities/receipt_window.py
receipt_dynamo/entities/receipt_word.py
receipt_dynamo/entities/receipt_word_tag.py
receipt_dynamo/entities/util.py
receipt_dynamo/entities/word.py
receipt_dynamo/entities/word_tag.py
receipt_dynamo-0.1.0.dist-info/METADATA
receipt_dynamo-0.1.0.dist-info/WHEEL
receipt_dynamo-0.1.0.dist-info/RECORD
