Metadata-Version: 2.4
Name: receipt-dynamo
Version: 0.1.0
Summary: A Python interface for accessing DynamoDB for receipt data processing and analysis
Project-URL: Homepage, https://github.com/tnorlund/example
Project-URL: Bug Tracker, https://github.com/tnorlund/example/issues
Author-email: Tyler Norlund <tnorlund@icloud.com>
Keywords: aws,database,dynamo,dynamodb,receipts
Classifier: Development Status :: 4 - Beta
Classifier: Intended Audience :: Developers
Classifier: License :: OSI Approved :: MIT License
Classifier: Operating System :: OS Independent
Classifier: Programming Language :: Python :: 3
Classifier: Programming Language :: Python :: 3.8
Classifier: Programming Language :: Python :: 3.9
Classifier: Programming Language :: Python :: 3.10
Classifier: Programming Language :: Python :: 3.11
Classifier: Programming Language :: Python :: 3.12
Classifier: Topic :: Database
Classifier: Topic :: Software Development :: Libraries :: Python Modules
Requires-Python: >=3.8
Requires-Dist: boto3>=1.26.0
Requires-Dist: pillow
Requires-Dist: requests
Provides-Extra: test
Requires-Dist: freezegun; extra == 'test'
Requires-Dist: moto; extra == 'test'
Requires-Dist: pytest; extra == 'test'
Requires-Dist: pytest-cov; extra == 'test'
Requires-Dist: pytest-mock; extra == 'test'
